pyezjson/__init__.py
pyezjson/connect/__init__.py
pyezjson/connect/connect.py
pyezjson-1.0.0.dist-info/LICENSE
pyezjson-1.0.0.dist-info/METADATA
pyezjson-1.0.0.dist-info/WHEEL
pyezjson-1.0.0.dist-info/top_level.txt
pyezjson-1.0.0.dist-info/RECORD
