Metadata-Version: 2.1
Name: pyezjson
Version: 1.0.0
Summary: Easier Json Database For Python
Home-page: https://github.com/M4hbod/pyezjson
Author: M4hbod
Author-email: M4hbod@proton.me
Project-URL: Bug Tracker, https://github.com/M4hbod/pyezjson/issues
Classifier: Programming Language :: Python :: 3
Classifier: License :: OSI Approved :: GNU General Public License v3 (GPLv3)
Classifier: Operating System :: OS Independent
Requires-Python: >=3.6
License-File: LICENSE
